{
  "$schema": "https://schemas.wp.org/trunk/block.json",
  "apiVersion": 3,
  "name": "cs/dynamic-feed",
  "version": "0.1.0",
  "title": "Dynamic Feed",
  "category": "widgets",
  "icon": "rss",
  "keywords": [
    "feed",
    "posts",
    "query",
    "category",
    "taxonomy"
  ],
  "description": "Display a dynamic feed of posts filtered by taxonomy terms, with SSR preview in the editor.",
  "example": {},
  "supports": {
    "html": false
  },
  "attributes": {
    "postType": {
      "type": "string",
      "default": "post"
    },
    "taxonomy": {
      "type": "string",
      "default": "category"
    },
    "termIds": {
      "type": "array",
      "items": {
        "type": "number"
      },
      "default": []
    },
    "orderBy": {
      "type": "string",
      "default": "date"
    },
    "order": {
      "type": "string",
      "default": "desc"
    },
    "limit": {
      "type": "number",
      "default": 6
    },
    "showImage": {
      "type": "boolean",
      "default": true
    },
    "showExcerpt": {
      "type": "boolean",
      "default": true
    },
    "excerptLength": {
      "type": "number",
      "default": 24
    },
    "showMeta": {
      "type": "boolean",
      "default": true
    },
    "viewStyle": {
      "type": "string",
      "default": "list"
    },
    "refreshKey": {
      "type": "number",
      "default": 0
    }
  },
  "textdomain": "cs-wordpress-blocks",
  "editorScript": "file:./index.js",
  "editorStyle": "file:./index.css",
  "style": "file:./style-index.css",
  "render": "file:./render.php",
  "viewScript": "file:./view.js"
}